MANIFEST.in
setup.py
Products/__init__.py
Products.PloneHotfix20130618.egg-info/PKG-INFO
Products.PloneHotfix20130618.egg-info/SOURCES.txt
Products.PloneHotfix20130618.egg-info/dependency_links.txt
Products.PloneHotfix20130618.egg-info/entry_points.txt
Products.PloneHotfix20130618.egg-info/namespace_packages.txt
Products.PloneHotfix20130618.egg-info/not-zip-safe
Products.PloneHotfix20130618.egg-info/requires.txt
Products.PloneHotfix20130618.egg-info/top_level.txt
Products/PloneHotfix20130618/README.txt
Products/PloneHotfix20130618/__init__.py
Products/PloneHotfix20130618/catalog.py
Products/PloneHotfix20130618/cb_decode.py
Products/PloneHotfix20130618/dataitems.py
Products/PloneHotfix20130618/get.py
Products/PloneHotfix20130618/imports.py
Products/PloneHotfix20130618/in_portal.py
Products/PloneHotfix20130618/linkintegrity.py
Products/PloneHotfix20130618/mail_password.py
Products/PloneHotfix20130618/marmoset_patch.py
Products/PloneHotfix20130618/member_portrait.py
Products/PloneHotfix20130618/objectmanager.py
Products/PloneHotfix20130618/principiaredirect.py
Products/PloneHotfix20130618/pts.py
Products/PloneHotfix20130618/publish.py
Products/PloneHotfix20130618/request.py
Products/PloneHotfix20130618/sendto.py
Products/PloneHotfix20130618/spamProtect.py
Products/PloneHotfix20130618/traverseName.py
Products/PloneHotfix20130618/traverser.py
Products/PloneHotfix20130618/typeswidget.py
Products/PloneHotfix20130618/wysiwyg.py
Products/PloneHotfix20130618/zip.py
dist/Products.PloneHotfix20130618-1.0/Products.PloneHotfix20130618.egg-info/SOURCES.txt
dist/Products.PloneHotfix20130618-1.0/Products.PloneHotfix20130618.egg-info/dependency_links.txt
dist/Products.PloneHotfix20130618-1.0/Products.PloneHotfix20130618.egg-info/entry_points.txt
dist/Products.PloneHotfix20130618-1.0/Products.PloneHotfix20130618.egg-info/namespace_packages.txt
dist/Products.PloneHotfix20130618-1.0/Products.PloneHotfix20130618.egg-info/requires.txt
dist/Products.PloneHotfix20130618-1.0/Products.PloneHotfix20130618.egg-info/top_level.txt
dist/Products.PloneHotfix20130618-1.0/Products/PloneHotfix20130618/README.txt
dist/Products.PloneHotfix20130618-1.0/docs/HISTORY.txt
dist/Products.PloneHotfix20130618-1.0/docs/INSTALL.txt
dist/Products.PloneHotfix20130618-1.0/docs/LICENSE.txt
dist/Products.PloneHotfix20130618-1.1/Products.PloneHotfix20130618.egg-info/SOURCES.txt
dist/Products.PloneHotfix20130618-1.1/Products.PloneHotfix20130618.egg-info/dependency_links.txt
dist/Products.PloneHotfix20130618-1.1/Products.PloneHotfix20130618.egg-info/entry_points.txt
dist/Products.PloneHotfix20130618-1.1/Products.PloneHotfix20130618.egg-info/namespace_packages.txt
dist/Products.PloneHotfix20130618-1.1/Products.PloneHotfix20130618.egg-info/requires.txt
dist/Products.PloneHotfix20130618-1.1/Products.PloneHotfix20130618.egg-info/top_level.txt
dist/Products.PloneHotfix20130618-1.1/Products/PloneHotfix20130618/README.txt
dist/Products.PloneHotfix20130618-1.1/dist/Products.PloneHotfix20130618-1.0/Products.PloneHotfix20130618.egg-info/SOURCES.txt
dist/Products.PloneHotfix20130618-1.1/dist/Products.PloneHotfix20130618-1.0/Products.PloneHotfix20130618.egg-info/dependency_links.txt
dist/Products.PloneHotfix20130618-1.1/dist/Products.PloneHotfix20130618-1.0/Products.PloneHotfix20130618.egg-info/entry_points.txt
dist/Products.PloneHotfix20130618-1.1/dist/Products.PloneHotfix20130618-1.0/Products.PloneHotfix20130618.egg-info/namespace_packages.txt
dist/Products.PloneHotfix20130618-1.1/dist/Products.PloneHotfix20130618-1.0/Products.PloneHotfix20130618.egg-info/requires.txt
dist/Products.PloneHotfix20130618-1.1/dist/Products.PloneHotfix20130618-1.0/Products.PloneHotfix20130618.egg-info/top_level.txt
dist/Products.PloneHotfix20130618-1.1/dist/Products.PloneHotfix20130618-1.0/Products/PloneHotfix20130618/README.txt
dist/Products.PloneHotfix20130618-1.1/dist/Products.PloneHotfix20130618-1.0/docs/HISTORY.txt
dist/Products.PloneHotfix20130618-1.1/dist/Products.PloneHotfix20130618-1.0/docs/INSTALL.txt
dist/Products.PloneHotfix20130618-1.1/dist/Products.PloneHotfix20130618-1.0/docs/LICENSE.txt
dist/Products.PloneHotfix20130618-1.1/docs/HISTORY.txt
dist/Products.PloneHotfix20130618-1.1/docs/INSTALL.txt
dist/Products.PloneHotfix20130618-1.1/docs/LICENSE.txt
docs/.HISTORY.txt.un~
docs/HISTORY.txt
docs/INSTALL.txt
