Metadata-Version: 1.1
Name: Products.PloneHotfix20130618
Version: 1.3
Summary: Various Plone hotfixes, 2013-06-18
Home-page: http://github.com/plone
Author: Plone Security Team
Author-email: security@plone.org
License: GPL
Keywords: plone security hotfix patch
Platform: UNKNOWN
Classifier: Framework :: Plone
Classifier: Programming Language :: Python
